[
  {
    "anonymous": false,
    "inputs": [
      {
        "indexed": false,
        "internalType": "address",
        "name": "admin",
        "type": "address"
      },
      {
        "indexed": false,
        "internalType": "address",
        "name": "nodesManager",
        "type": "address"
      },
      {
        "indexed": false,
        "internalType": "uint256",
        "name": "capacity",
        "type": "uint256"
      },
      {
        "indexed": false,
        "internalType": "uint16",
        "name": "feePercent",
        "type": "uint16"
      },
      {
        "indexed": false,
        "internalType": "string",
        "name": "name",
        "type": "string"
      },
      {
        "indexed": false,
        "internalType": "string",
        "name": "symbol",
        "type": "string"
      },
      {
        "indexed": false,
        "internalType": "string",
        "name": "metadataIpfsHash",
        "type": "string"
      }
    ],
    "name": "EthCommunityVaultCreated",
    "type": "event"
  }
]
